urdfpy/__init__.py
urdfpy/urdf.py
urdfpy/utils.py
urdfpy/version.py
urdfpy-0.0.20.dist-info/LICENSE
urdfpy-0.0.20.dist-info/METADATA
urdfpy-0.0.20.dist-info/WHEEL
urdfpy-0.0.20.dist-info/top_level.txt
urdfpy-0.0.20.dist-info/RECORD
